vio/__init__.py
vio/actions.py
vio/clients.py
vio/exceptions.py
vio/utils.py
vio/scripts/__init__.py
vio/scripts/vio.py
vio_cli-0.2.0.dist-info/METADATA
vio_cli-0.2.0.dist-info/WHEEL
vio_cli-0.2.0.dist-info/entry_points.txt
vio_cli-0.2.0.dist-info/top_level.txt
vio_cli-0.2.0.dist-info/RECORD
