Metadata-Version: 2.1
Name: vio-cli
Version: 0.2.0
Requires-Dist: boto3
Requires-Dist: click
Requires-Dist: requests
